sideload_helm_v3_bin_6718272be41b4d34e4472c13/__init__.py
sideload_helm_v3_bin_6718272be41b4d34e4472c13/helm-v3.16.2-windows-amd64.zip
sideload_helm_v3_bin_6718272be41b4d34e4472c13-1.0.0.dist-info/METADATA
sideload_helm_v3_bin_6718272be41b4d34e4472c13-1.0.0.dist-info/WHEEL
sideload_helm_v3_bin_6718272be41b4d34e4472c13-1.0.0.dist-info/top_level.txt
sideload_helm_v3_bin_6718272be41b4d34e4472c13-1.0.0.dist-info/RECORD
