Metadata-Version: 2.1
Name: sideload_helm_v3_bin_6718272be41b4d34e4472c13
Version: 1.0.0
Summary: Sideloaded package
Author: Null Void
Requires-Python: >=3.8
